web_scraping_mcp/__init__.py
web_scraping_mcp/cli.py
web_scraping_mcp/config.py
web_scraping_mcp/exceptions.py
web_scraping_mcp/logging_setup.py
web_scraping_mcp/models.py
web_scraping_mcp/schema_builder.py
web_scraping_mcp/scraping_manager.py
web_scraping_mcp/server.py
realtimex_web_scraping_mcp_server-0.1.0.dist-info/METADATA
realtimex_web_scraping_mcp_server-0.1.0.dist-info/WHEEL
realtimex_web_scraping_mcp_server-0.1.0.dist-info/entry_points.txt
realtimex_web_scraping_mcp_server-0.1.0.dist-info/RECORD
