Metadata-Version: 2.4
Name: realtimex-web-scraping-mcp-server
Version: 0.1.0
Summary: A Model Context Protocol (MCP) server for web scraping using Crawl4AI
Author-email: RealTimeX <inf@realtimex.ai>
License: MIT
Keywords: automation,crawl4ai,data-extraction,mcp,web-scraping
Requires-Python: >=3.10
Requires-Dist: crawl4ai>=0.6.0
Requires-Dist: cssselect>=1.3.0
Requires-Dist: mcp>=1.0.0
Requires-Dist: pydantic>=2.0.0
Requires-Dist: structlog>=23.0.0
Requires-Dist: tenacity>=8.0.0
